odoo/addons/helpdesk_mgmt_sale/README.rst
odoo/addons/helpdesk_mgmt_sale/__init__.py
odoo/addons/helpdesk_mgmt_sale/__manifest__.py
odoo/addons/helpdesk_mgmt_sale/i18n/de.po
odoo/addons/helpdesk_mgmt_sale/i18n/es.po
odoo/addons/helpdesk_mgmt_sale/i18n/fr.po
odoo/addons/helpdesk_mgmt_sale/i18n/helpdesk_mgmt_sale.pot
odoo/addons/helpdesk_mgmt_sale/i18n/it.po
odoo/addons/helpdesk_mgmt_sale/i18n/pt_BR.po
odoo/addons/helpdesk_mgmt_sale/i18n/sv.po
odoo/addons/helpdesk_mgmt_sale/models/__init__.py
odoo/addons/helpdesk_mgmt_sale/models/helpdesk_ticket.py
odoo/addons/helpdesk_mgmt_sale/models/sale_order.py
odoo/addons/helpdesk_mgmt_sale/readme/CONTRIBUTORS.md
odoo/addons/helpdesk_mgmt_sale/readme/DESCRIPTION.md
odoo/addons/helpdesk_mgmt_sale/readme/USAGE.md
odoo/addons/helpdesk_mgmt_sale/security/ir.model.access.csv
odoo/addons/helpdesk_mgmt_sale/static/description/icon.png
odoo/addons/helpdesk_mgmt_sale/static/description/icon.svg
odoo/addons/helpdesk_mgmt_sale/static/description/index.html
odoo/addons/helpdesk_mgmt_sale/tests/__init__.py
odoo/addons/helpdesk_mgmt_sale/tests/test_helpdesk_ticket.py
odoo/addons/helpdesk_mgmt_sale/views/helpdesk_ticket_views.xml
odoo/addons/helpdesk_mgmt_sale/views/sale_order_views.xml
odoo/addons/helpdesk_mgmt_sale/wizards/__init__.py
odoo/addons/helpdesk_mgmt_sale/wizards/helpdesk_ticket_link_sale_order.py
odoo/addons/helpdesk_mgmt_sale/wizards/helpdesk_ticket_link_sale_order.xml
odoo_addon_helpdesk_mgmt_sale-18.0.2.0.1.dist-info/METADATA
odoo_addon_helpdesk_mgmt_sale-18.0.2.0.1.dist-info/WHEEL
odoo_addon_helpdesk_mgmt_sale-18.0.2.0.1.dist-info/top_level.txt
odoo_addon_helpdesk_mgmt_sale-18.0.2.0.1.dist-info/RECORD
